codemie_sdk/__init__.py
codemie_sdk/auth/__init__.py
codemie_sdk/auth/credentials.py
codemie_sdk/client/__init__.py
codemie_sdk/client/client.py
codemie_sdk/exceptions.py
codemie_sdk/models/__init__.py
codemie_sdk/models/admin.py
codemie_sdk/models/analytics.py
codemie_sdk/models/assistant.py
codemie_sdk/models/categories.py
codemie_sdk/models/common.py
codemie_sdk/models/conversation.py
codemie_sdk/models/datasource.py
codemie_sdk/models/file_operation.py
codemie_sdk/models/guardrails.py
codemie_sdk/models/integration.py
codemie_sdk/models/llm.py
codemie_sdk/models/mermaid.py
codemie_sdk/models/task.py
codemie_sdk/models/user.py
codemie_sdk/models/vendor_assistant.py
codemie_sdk/models/vendor_guardrail.py
codemie_sdk/models/vendor_knowledgebase.py
codemie_sdk/models/vendor_workflow.py
codemie_sdk/models/workflow.py
codemie_sdk/models/workflow_execution_payload.py
codemie_sdk/models/workflow_state.py
codemie_sdk/models/workflow_thoughts.py
codemie_sdk/services/admin.py
codemie_sdk/services/analytics.py
codemie_sdk/services/assistant.py
codemie_sdk/services/categories.py
codemie_sdk/services/codemie_guardrails.py
codemie_sdk/services/conversation.py
codemie_sdk/services/datasource.py
codemie_sdk/services/files.py
codemie_sdk/services/integration.py
codemie_sdk/services/llm.py
codemie_sdk/services/mermaid.py
codemie_sdk/services/task.py
codemie_sdk/services/user.py
codemie_sdk/services/vendor_assistant.py
codemie_sdk/services/vendor_guardrail.py
codemie_sdk/services/vendor_knowledgebase.py
codemie_sdk/services/vendor_workflow.py
codemie_sdk/services/webhook.py
codemie_sdk/services/workflow.py
codemie_sdk/services/workflow_execution.py
codemie_sdk/services/workflow_execution_state.py
codemie_sdk/utils/__init__.py
codemie_sdk/utils/http.py
codemie_sdk_python-0.1.322.dist-info/METADATA
codemie_sdk_python-0.1.322.dist-info/WHEEL
codemie_sdk_python-0.1.322.dist-info/RECORD
