Metadata-Version: 2.1
Name: codemie-sdk-python
Version: 0.1.322
Summary: CodeMie SDK for Python
Author: Vadym Vlasenko
Author-email: vadym_vlasenko@epam.com
Requires-Python: >=3.12,<4.0
Classifier: Programming Language :: Python :: 3
Classifier: Programming Language :: Python :: 3.12
Requires-Dist: pydantic (>=2.12.2,<3.0.0)
Requires-Dist: requests (>=2.31.0,<3.0.0)
